apispec_marshmallow_advanced/__init__.py
apispec_marshmallow_advanced/common.py
apispec_marshmallow_advanced/openapi.py
apispec_marshmallow_advanced-0.4.data/data/LICENSE
apispec_marshmallow_advanced-0.4.dist-info/LICENSE
apispec_marshmallow_advanced-0.4.dist-info/METADATA
apispec_marshmallow_advanced-0.4.dist-info/WHEEL
apispec_marshmallow_advanced-0.4.dist-info/top_level.txt
apispec_marshmallow_advanced-0.4.dist-info/RECORD
